first_dance/__init__.py
first_dance/core/doc.cpython-312-x86_64-linux-gnu.so
first_dance/core/pdf.cpython-312-x86_64-linux-gnu.so
first_dance-0.1.14.dist-info/METADATA
first_dance-0.1.14.dist-info/WHEEL
first_dance-0.1.14.dist-info/top_level.txt
first_dance-0.1.14.dist-info/RECORD
